cos/__init__.py
cos/cli.py
cos/config.py
cos/utils.py
cos/commands/__init__.py
cos/commands/cmd_clean.py
cos/commands/cmd_init.py
cos/commands/cmd_tasks.py
cos/commands/cmd_venv.py
cos/meta/init/templates/python.json
cos/scripts/cosenv
cos/scripts/cosenv.bat
cos/services/__init__.py
cos/services/svc_clean.py
cos/services/svc_init.py
cos/services/svc_tasks.py
cos/services/svc_venv.py
cospy-0.4.2.data/scripts/cosenv
cospy-0.4.2.data/scripts/cosenv.bat
cospy-0.4.2.dist-info/LICENSE
cospy-0.4.2.dist-info/METADATA
cospy-0.4.2.dist-info/WHEEL
cospy-0.4.2.dist-info/entry_points.txt
cospy-0.4.2.dist-info/top_level.txt
cospy-0.4.2.dist-info/RECORD
